rubric_agent-0.0.7.dist-info/licenses/LICENSE.txt
rubricagent/__init__.py
rubricagent/agent.py
rubricagent/chains.py
rubricagent/main.py
rubricagent/nodes.py
rubricagent/rubric_app.py
rubricagent/server.py
rubricagent/state.py
rubricagent/tools.py
rubric_agent-0.0.7.dist-info/METADATA
rubric_agent-0.0.7.dist-info/WHEEL
rubric_agent-0.0.7.dist-info/entry_points.txt
rubric_agent-0.0.7.dist-info/top_level.txt
rubric_agent-0.0.7.dist-info/RECORD
