Metadata-Version: 2.4
Name: rubric-agent
Version: 0.0.7
Summary: 학생 과제 루브릭 생성 및 피드백을 제공하는 MCP 서버
Author-email: Jongbok Lee <jongbok.data0319@gmail.com>
Requires-Python: >=3.11
License-File: LICENSE.txt
Requires-Dist: build>=1.2.2.post1
Requires-Dist: fastapi>=0.115.12
Requires-Dist: google-search-results==2.4.2
Requires-Dist: langchain==0.3.21
Requires-Dist: langchain-cohere==0.4.3
Requires-Dist: langchain-community==0.3.20
Requires-Dist: langchain-core==0.3.46
Requires-Dist: langchain-experimental==0.3.4
Requires-Dist: langchain-google-genai==2.1.0
Requires-Dist: langchain-openai==0.3.9
Requires-Dist: langchain-teddynote==0.3.44
Requires-Dist: langchain-text-splitters==0.3.7
Requires-Dist: langchainhub==0.1.21
Requires-Dist: langgraph==0.3.18
Requires-Dist: mcp>=1.9.3
Requires-Dist: openai==1.67.0
Requires-Dist: openai-agents>=0.0.12
Requires-Dist: python-dotenv==1.0.1
Requires-Dist: tiktoken==0.9.0
Requires-Dist: twine>=6.1.0
Requires-Dist: uvicorn>=0.34.3
Dynamic: license-file
